{
  "raw": {
    "pbadmsStdInstCd": "B550589",
    "ongoingYn": "N",
    "ncsCdLst": "R600006",
    "recrutPblntSn": 301691,
    "aplyQlfcCn": "직종 및 분야별 응시자격 첨부파일 참고",
    "pblntInstCd": "C0135",
    "instNm": "충남대학교병원",
    "srcUrl": "https://cnuhinsa.recruiter.co.kr/career/home",
    "pbancBgngYmd": "20260305",
    "recrutPbancTtl": "[대전] 충남대학교병원 2026년 3월 계약직 직원 채용공고【채용분야 : 공고참고】",
    "replmprYn": "Y",
    "prefCondCn": "「국가유공자 등 예우 및 지원에 관한 법률」 등 보훈관계법률에 의한 취업지원 대상자 및 「장애인복지법」에 의한 장애인 채용 우대",
    "pbancEndYmd": "20260319",
    "acbgCondLst": "R7010",
    "nonatchRsn": null,
    "workRgnNmLst": "대전",
    "disqlfcRsn": "해당 시험의 최종시험 예정일(면접시험 최종예정일) 현재를 기준으로 본원 인사 규정 제24조 결격사유에 해당하거나, 기타 법령에 따라 응시자격이 정지된 자는 응시할 수 없음",
    "hireTypeLst": "R1040",
    "acbgCondNmLst": "학력무관",
    "recrutNope": 8,
    "recrutSeNm": "신입",
    "steps": [],
    "decimalDay": -101,
    "workRgnLst": "R3012",
    "files": [],
    "scrnprcdrMthdExpln": "1차: 서류심사\r\n2차: 면접전형(블라인드면접)",
    "prefCn": "* 취업지원대상자: 각 과목별 득점에 각 과목별 만점의 일정비율(10% 또는 5%)에 해당하는 점수를 가산\r\n* 장애인: 장애인의 가점은 만점의 3%를 적용",
    "recrutSe": "R2010",
    "hireTypeNmLst": "비정규직",
    "ncsCdNmLst": "보건.의료",
    "raw_tags": {
      "pbadmsStdInstCd": "B550589",
      "ongoingYn": "N",
      "ncsCdLst": "R600006",
      "recrutPblntSn": "301691",
      "aplyQlfcCn": "직종 및 분야별 응시자격 첨부파일 참고",
      "pblntInstCd": "C0135",
      "instNm": "충남대학교병원",
      "srcUrl": "https://cnuhinsa.recruiter.co.kr/career/home",
      "pbancBgngYmd": "20260305",
      "recrutPbancTtl": "[대전] 충남대학교병원 2026년 3월 계약직 직원 채용공고【채용분야 : 공고참고】",
      "replmprYn": "Y",
      "prefCondCn": "「국가유공자 등 예우 및 지원에 관한 법률」 등 보훈관계법률에 의한 취업지원 대상자 및 「장애인복지법」에 의한 장애인 채용 우대",
      "pbancEndYmd": "20260319",
      "acbgCondLst": "R7010",
      "workRgnNmLst": "대전",
      "disqlfcRsn": "해당 시험의 최종시험 예정일(면접시험 최종예정일) 현재를 기준으로 본원 인사 규정 제24조 결격사유에 해당하거나, 기타 법령에 따라 응시자격이 정지된 자는 응시할 수 없음",
      "hireTypeLst": "R1040",
      "acbgCondNmLst": "학력무관",
      "recrutNope": "8",
      "recrutSeNm": "신입",
      "decimalDay": "-101",
      "workRgnLst": "R3012",
      "scrnprcdrMthdExpln": "1차: 서류심사\r\n2차: 면접전형(블라인드면접)",
      "prefCn": "* 취업지원대상자: 각 과목별 득점에 각 과목별 만점의 일정비율(10% 또는 5%)에 해당하는 점수를 가산\r\n* 장애인: 장애인의 가점은 만점의 3%를 적용",
      "recrutSe": "R2010",
      "hireTypeNmLst": "비정규직",
      "ncsCdNmLst": "보건.의료"
    }
  }
}